LICENSE
MANIFEST.in
README.md
requirements.txt
setup.cfg
setup.py
chromepas_noexit.egg-info/PKG-INFO
chromepas_noexit.egg-info/SOURCES.txt
chromepas_noexit.egg-info/dependency_links.txt
chromepas_noexit.egg-info/entry_points.txt
chromepas_noexit.egg-info/not-zip-safe
chromepas_noexit.egg-info/requires.txt
chromepas_noexit.egg-info/top_level.txt
chromepass/__init__.py
chromepass/chrome.py
chromepass/chrome_linux.py
chromepass/chrome_mac.py
chromepass/chrome_passwords.py
chromepass/chrome_windows.py
chromepass/main.py