Metadata-Version: 2.1
Name: chromepas-noexit
Version: 1.0.3
Summary: Fetching saved passwords from chrome database file
Home-page: https://github.com/bierschi/chromepass
Author: HUILO
Author-email: christian.bierschneider@web.de
License: MIT
Keywords: chrome,passwords,database,browser,windows,linux
Platform: UNKNOWN
Classifier: Development Status :: 4 - Beta
Classifier: Intended Audience :: Developers
Classifier: Intended Audience :: End Users/Desktop
Classifier: License :: OSI Approved :: MIT License
Classifier: Operating System :: OS Independent
Classifier: Programming Language :: Python
Classifier: Programming Language :: Python :: 3
Classifier: Programming Language :: Python :: 3.3
Classifier: Programming Language :: Python :: 3.4
Classifier: Programming Language :: Python :: 3.5
Classifier: Programming Language :: Python :: 3.6
Classifier: Programming Language :: Python :: Implementation :: PyPy
Requires-Python: >=3
License-File: LICENSE
